setup.py
calaccess/__init__.py
calaccess/admin.py
calaccess/managers.py
calaccess/models.py
calaccess/tests.py
calaccess/views.py
calaccess/management/__init__.py
calaccess/management/commands/__init__.py
calaccess/management/commands/cleancalaccessfile.py
calaccess/management/commands/downloadcalaccess.py
calaccess/management/commands/loadcalaccessfile.py
django_calaccess_parser.egg-info/PKG-INFO
django_calaccess_parser.egg-info/SOURCES.txt
django_calaccess_parser.egg-info/dependency_links.txt
django_calaccess_parser.egg-info/requires.txt
django_calaccess_parser.egg-info/top_level.txt