Metadata-Version: 1.0
Name: django-calaccess-parser
Version: 0.5
Summary: A Django app to download, extract and load campaign finance and lobbying activity data from the California Secretary of State's CAL-ACCESS database
Home-page: https://github.com/california-civic-data-coalition
Author: California Civic Data Coalition
Author-email: ben.welsh@latimes.com
License: MIT
Platform: UNKNOWN
